konBfApi/__init__.py
konBfApi/exceptions.py
konBfApi/main.py
k0napi-0.0.3.dist-info/METADATA
k0napi-0.0.3.dist-info/WHEEL
k0napi-0.0.3.dist-info/top_level.txt
k0napi-0.0.3.dist-info/RECORD
