Metadata-Version: 2.1
Name: k0napi
Version: 0.0.3
Summary: k-0n bf1 api sdk
Home-page: https://github.com/
Author: SuzuBucket
Author-email: root@k-0n.org
License: UNKNOWN
Platform: UNKNOWN
Requires-Dist: httpx[http2] (==0.21.1)
